lighter/__init__.py
lighter/callbacks/__init__.py
lighter/callbacks/freezer.py
lighter/callbacks/utils.py
lighter/callbacks/writer/__init__.py
lighter/callbacks/writer/base.py
lighter/callbacks/writer/file.py
lighter/callbacks/writer/table.py
lighter/system.py
lighter/utils/__init__.py
lighter/utils/collate.py
lighter/utils/dynamic_imports.py
lighter/utils/logging.py
lighter/utils/misc.py
lighter/utils/model.py
lighter/utils/runner.py
project_lighter-0.0.2.dist-info/LICENSE
project_lighter-0.0.2.dist-info/METADATA
project_lighter-0.0.2.dist-info/WHEEL
project_lighter-0.0.2.dist-info/entry_points.txt
project_lighter-0.0.2.dist-info/RECORD
